pybd_miniapp/__init__.py
pybd_miniapp/miniapp.py
pybd_miniapp-1.0.0.dist-info/METADATA
pybd_miniapp-1.0.0.dist-info/WHEEL
pybd_miniapp-1.0.0.dist-info/top_level.txt
pybd_miniapp-1.0.0.dist-info/RECORD
