Metadata-Version: 2.1
Name: pybd-miniapp
Version: 1.0.0
Summary: Baidu SmartProgram Module for Python for MiniApp.
Home-page: https://github.com/sdkwe/pybd-miniapp
Author: Hackathon
Author-email: kimi.huang@brightcells.com
License: UNKNOWN
Keywords: Baidu SmartProgram Mini App
Platform: UNKNOWN
Classifier: License :: OSI Approved :: BSD License
Classifier: Programming Language :: Python
Classifier: Programming Language :: Python :: 2
Classifier: Programming Language :: Python :: 2.6
Classifier: Programming Language :: Python :: 2.7
Classifier: Programming Language :: Python :: 3
Classifier: Programming Language :: Python :: 3.2
Classifier: Programming Language :: Python :: 3.3
Classifier: Programming Language :: Python :: 3.4
Classifier: Topic :: Software Development :: Libraries :: Python Modules
Requires-Dist: pybd-base
Requires-Dist: pybd-decrypt
Requires-Dist: pywe-storage
